AUTHORS.rst
CONTRIBUTING.rst
HISTORY.rst
LICENSE
MANIFEST.in
README.rst
setup.cfg
setup.py
docs/Makefile
docs/authors.rst
docs/conf.py
docs/contributing.rst
docs/history.rst
docs/index.rst
docs/installation.rst
docs/make.bat
docs/readme.rst
docs/usage.rst
stoneredis/__init__.py
stoneredis/client.py
stoneredis_test.egg-info/PKG-INFO
stoneredis_test.egg-info/SOURCES.txt
stoneredis_test.egg-info/dependency_links.txt
stoneredis_test.egg-info/not-zip-safe
stoneredis_test.egg-info/requires.txt
stoneredis_test.egg-info/top_level.txt
tests/__init__.py
tests/test_stoneredis.py